{"0": "UI Components & View Models", "1": "Server Actions & Occurrences", "2": "NPM Dependencies", "3": "Today Page & Freshness", "4": "Auth & HA Integration", "5": "Architecture Design Docs", "6": "App Layout & Navigation", "7": "shadcn Components Config", "8": "TypeScript Config", "9": "Freshness UI Badges", "10": "Next.js Config", "11": "UI Icon SVGs", "12": "Next.js Fork Warning", "13": "ESLint Config", "14": "PostCSS Config", "15": "Brand Logos", "16": "MQTT Sensor (Phase 2)", "17": "Robots.txt"}